ARGE/ARGE.py
ARGE/__init__.py
ARGE-0.0.1.dist-info/LICENSE.md
ARGE-0.0.1.dist-info/METADATA
ARGE-0.0.1.dist-info/WHEEL
ARGE-0.0.1.dist-info/entry_points.txt
ARGE-0.0.1.dist-info/top_level.txt
ARGE-0.0.1.dist-info/RECORD
