Metadata-Version: 2.1
Name: ARGE
Version: 0.0.1
Summary: A small example package
Home-page: UNKNOWN
Author: Guilhem Servant
Author-email: author@example.com
License: UNKNOWN
Platform: UNKNOWN
Classifier: Programming Language :: Python :: 3
Classifier: License :: OSI Approved :: MIT License
Classifier: Operating System :: OS Independent
Requires-Dist: pandas (>=0.21.0)
Requires-Dist: numpy
